10-full_adder/full_adder_1b.v
// 1bit full adder

module full_adder_1b (
    input wire a,
    input wire b,
    input wire cin,
    output wire s,
    output wire cout

);

assign {cout, s} = a + b + cin; // Concatenation operator
// The sum is the least significant bit (LSB) and the carry out is the most significant bit (MSB)


endmodule

10-full_adder/tb_full_adder_1b.v
`timescale 1ns/1ps
`include "full_adder_1b.v"

module tb();

    // Inputs
    reg a;
    reg b;
    reg cin;


    // Output
    wire s;
    wire cout;

    // Instantiate the Unit Under Test (UUT)
    full_adder_1b uut (
        .a(a),
        .b(b),
        .cin(cin),
        .s(s),
        .cout(cout)

    );

    initial begin
        $dumpfile("full_adder_1b_dump.vcd");
        $dumpvars(0, tb);

        // Test cases
        a = 0; b = 0; cin = 0; #10;
        a = 0; b = 0; cin = 1; #10;
        a = 0; b = 1; cin = 0; #10;
        a = 0; b = 1; cin = 1; #10;
        a = 1; b = 0; cin = 0; #10;
        a = 1; b = 0; cin = 1; #10;
        a = 1; b = 1; cin = 0; #10;
        a = 1; b = 1; cin = 1; #10;

        $finish;
    end

    initial begin
        $monitor("Time=%0t | a=%b b=%b cin=%b | s=%b cout=%b ", 
                 $time, a, b, cin, s, cout);
    end

endmodule

10-full_adder/full_adder_1b_dump.vcd
$date
	Tue Apr 29 14:11:10 2025
$end
$version
	Icarus Verilog
$end
$timescale
	1ps
$end
$scope module tb $end
$var wire 1 ! s $end
$var wire 1 " cout $end
$var reg 1 # a $end
$var reg 1 $ b $end
$var reg 1 % cin $end
$scope module uut $end
$var wire 1 # a $end
$var wire 1 $ b $end
$var wire 1 % cin $end
$var wire 1 ! s $end
$var wire 1 " cout $end
$upscope $end
$upscope $end
$enddefinitions $end
#0
$dumpvars
0%
0$
0#
0"
0!
$end
#10000
1!
1%
#20000
0%
1$
#30000
0!
1"
1%
#40000
0"
1!
0%
0$
1#
#50000
0!
1"
1%
#60000
0%
1$
#70000
1!
1%
