12-d_flipflop/d_flipflop.v
// Description: D Flip-Flop 1 Bit

/* 
1. Reset Signal

If the reset signal is active on the positive edge (i.e., asynchronous or synchronous positive-edge reset), 
then on the rising edge of the reset signal, the output is immediately set to 0, 
regardless of the input or clock

After the reset is asserted (output is 0), the output will hold this value until the reset signal goes low 
(i.e., reset is de-asserted)

This is typical for an asynchronous reset. 
For a synchronous reset, the output would only reset to 0 on the clock edge if reset is high at that moment.


2. Enable Signal

When the reset is not active (reset is low), the output will follow the input value (D) only 
when the enable signal is high and on the positive edge of the clock

If enable is low, the output holds its previous value, regardless of the input or clock

3. Clock Signal

The D flip-flop is edge-triggered (usually positive edge). 
The output changes only on the rising edge of the clock, provided that enable is high and reset is not active
*/


module d_flipflop(
    input wire d, 
    input wire en,
    input wire clk, // Clock input
    input wire rst, // Reset input

    output reg q

);

always @ (posedge clk or posedge rst) begin // Sensitivity list
    if (rst) begin
        q <= 0; // If enable is high, output follows input
    end

    else if (en) begin
        q <= d; // If enable is high, output follows input
        
        
        /* 
        
        <= - Non-blocking assignment operator, used for sequential logic
         = - Blocking assignment operator

         example:

         Let's say x = 3, y = 7

            x = y; // x will be 7
            z = x; // z will be 7

        But if we use non-blocking assignment operator

            x <= y; // x will be 7
            z <= x; // z will be 3

         */
         
    end

end

endmodule

12-d_flipflop/d_flipflop_tb.v
// This is the testbench for the D flip-flop module

`include "d_flipflop.v"
`timescale 1ns / 1ps

module tb_d_flipflop;

    // Inputs
    reg d;
    reg en;
    reg clk;
    reg rst;

    // Output
    wire q;

    // Instantiate the Unit Under Test (UUT)
    d_flipflop uut (
        .d(d),
        .en(en),
        .clk(clk),
        .rst(rst),
        .q(q)
    );

    initial begin
        $dumpfile("dump.vcd");
        $dumpvars(0, tb_d_flipflop);
    end

    initial begin
        // Clock generation
        clk <=0;
        forever begin
            #5 clk <= ~clk; // Toggle clock every 5 time units
        end
    end

    
    initial begin

        // Initialize inputs
        d = 0;
        en = 0;
        rst = 0;

        // Test cases
        #3 en = 1; d = 1;
        #15 d = 0;
        #5 en = 0;
        #5 d = 1;
        #5 d = 0;
        #5 en = 1;
        #5 d = 1;
        #10 rst = 1;
        #10 rst = 0; 
        #10 en = 0; 
        #10 d = 0;
        #10 en = 1;
        #7 $finish;

    end

    initial begin
        // Monitor the output
        $monitor("Time=%0t | d=%b en=%b clk=%b rst=%b | q=%b", 
                 $time, d, en, clk, rst, q);
    end

endmodule

12-d_flipflop/dump.vcd
$date
	Tue May 20 14:40:38 2025
$end
$version
	Icarus Verilog
$end
$timescale
	1ps
$end
$scope module tb_d_flipflop $end
$var wire 1 ! q $end
$var reg 1 " clk $end
$var reg 1 # d $end
$var reg 1 $ en $end
$var reg 1 % rst $end
$scope module uut $end
$var wire 1 " clk $end
$var wire 1 # d $end
$var wire 1 $ en $end
$var wire 1 % rst $end
$var reg 1 ! q $end
$upscope $end
$upscope $end
$enddefinitions $end
#0
$dumpvars
0%
0$
0#
0"
x!
$end
#3000
1#
1$
#5000
1!
1"
#10000
0"
#15000
1"
#18000
0#
#20000
0"
#23000
0$
#25000
1"
#28000
1#
#30000
0"
#33000
0#
#35000
1"
#38000
1$
#40000
0"
#43000
1#
#45000
1"
#50000
0"
#53000
0!
1%
#55000
1"
#60000
0"
#63000
0%
#65000
1!
1"
#70000
0"
#73000
0$
#75000
1"
#80000
0"
#83000
0#
#85000
1"
#90000
0"
#93000
1$
#95000
0!
1"
