15-fsm/fsm-moor.v
module divide_by3fsm (
    input reset,
    input clk,
    output y,
    output [2:0] state,      // Add this line
    output [2:0] nextstate   // Add this line
);

reg [2:0] state_reg, nextstate_reg;

parameter S0 = 3'b000, // state 0
          S1 = 3'b001, // state 1
          S2 = 3'b010; // state 2

always @ (posedge clk or posedge reset) begin
    if (reset) begin
        state_reg <= S0; // reset to state 0
    end 
    else begin
        state_reg <= nextstate_reg; // transition to next state
    end
end

// Next state logic
always @ (*) begin
    case (state_reg)
        S0: nextstate_reg = S1;
        S1: nextstate_reg = S2;
        S2: nextstate_reg = S0;
        default: nextstate_reg = S0; // reset to state 0
    endcase
end

// Output logic
assign y = (state_reg == S0);

// Debug outputs
assign state = state_reg;
assign nextstate = nextstate_reg;

endmodule

15-fsm/fsm-moor-tb.v
`timescale 1ns / 1ps
`include "fsm-moor.v"

module fsm_moor_tb;

    reg clk;
    reg reset;
    wire y;
    wire [2:0] state;
    wire [2:0] nextstate;

    divide_by3fsm uut (
        .clk(clk),
        .reset(reset),
        .y(y),
        .state(state),
        .nextstate(nextstate)
    );

    initial begin
        $dumpfile("dump.vcd");
        $dumpvars(0, fsm_moor_tb);
    end

    // Clock generation
    initial begin
        clk = 0;
        forever #5 clk = ~clk;
    end

    // Test sequence
    initial begin
        $display("Starting FSM Moore Testbench...");
        reset = 1;
        #12;
        reset = 0;
        #100;
        $finish;
    end

    // Monitor outputs
    initial begin
        $monitor("Time=%0t | reset=%b | y=%b | state=%b | nextstate=%b", $time, reset, y, state, nextstate);
    end

endmodule

15-fsm/dump.vcd
$date
	Tue May 27 15:27:07 2025
$end
$version
	Icarus Verilog
$end
$timescale
	1ps
$end
$scope module fsm_moor_tb $end
$var wire 1 ! y $end
$var wire 3 " state [2:0] $end
$var wire 3 # nextstate [2:0] $end
$var reg 1 $ clk $end
$var reg 1 % reset $end
$scope module uut $end
$var wire 1 $ clk $end
$var wire 3 & nextstate [2:0] $end
$var wire 1 % reset $end
$var wire 3 ' state [2:0] $end
$var wire 1 ! y $end
$var reg 3 ( nextstate_reg [2:0] $end
$var reg 3 ) state_reg [2:0] $end
$upscope $end
$upscope $end
$enddefinitions $end
#0
$dumpvars
b0 )
b1 (
b0 '
b1 &
1%
0$
b1 #
b0 "
1!
$end
#5000
1$
#10000
0$
#12000
0%
#15000
b10 #
b10 &
b10 (
0!
b1 "
b1 '
b1 )
1$
#20000
0$
#25000
b0 #
b0 &
b0 (
b10 "
b10 '
b10 )
1$
#30000
0$
#35000
b1 #
b1 &
b1 (
1!
b0 "
b0 '
b0 )
1$
#40000
0$
#45000
b10 #
b10 &
b10 (
0!
b1 "
b1 '
b1 )
1$
#50000
0$
#55000
b0 #
b0 &
b0 (
b10 "
b10 '
b10 )
1$
#60000
0$
#65000
b1 #
b1 &
b1 (
1!
b0 "
b0 '
b0 )
1$
#70000
0$
#75000
b10 #
b10 &
b10 (
0!
b1 "
b1 '
b1 )
1$
#80000
0$
#85000
b0 #
b0 &
b0 (
b10 "
b10 '
b10 )
1$
#90000
0$
#95000
b1 #
b1 &
b1 (
1!
b0 "
b0 '
b0 )
1$
#100000
0$
#105000
b10 #
b10 &
b10 (
0!
b1 "
b1 '
b1 )
1$
