16-fsm_button/button.v
module button
(
    input wire reset,
    input wire clk,
    input wire button,

    output reg led

);

parameter LED_ON = 1'b1;
parameter LED_OFF = 1'b0;

reg status;
parameter STATE_LEDON = 1'b1;
parameter STATE_LEDOFF = 1'b0;

parameter BTN_PRESSED = 1'b1;
parameter BTN_RELEASED = 1'b0;



always @(posedge clk or posedge reset) begin
    if (reset) begin
        led <= LED_OFF; // Reset the LED to OFF state
    end 

    else begin
        case (status)
            STATE_LEDON: begin
                if (button == BTN_RELEASED) begin
                    status <= STATE_LEDOFF;
                    led <= LED_OFF; // Turn OFF the LED when button is released
                end

                else begin
                    led <= LED_ON; // Keep the LED ON if button is pressed
                end

            end

            STATE_LEDOFF: begin
                if (button == BTN_PRESSED) begin
                    status <= STATE_LEDON;
                    led <= LED_ON; // Turn ON the LED when button is pressed
                end

                else begin
                    led <= LED_OFF; // Keep the LED OFF if button is not pressed
                end

            end

        endcase
    end
    

end
    
endmodule

16-fsm_button/button_tb.v
`timescale 1ns / 1ps
`include "button.v"

module button_tb;

    reg clk;
    reg reset;
    reg button;

    wire led;


    button uut (
        .clk(clk),
        .reset(reset),
        .button(button),
        
        .led(led)
    );

    initial begin
        $dumpfile("dump.vcd");
        $dumpvars(0, button_tb);
    end

    // Clock generation
    initial begin
        clk = 0;
        forever #5 clk = ~clk;
    end

    // Test sequence
    initial begin
        reset = 0; button = 0; #12;
        button = 1; #10;
        button = 0; #10;
        button = 1; #10;

        reset = 1; #10; // Reset the FSM
        reset = 0; #10; // Release reset    
        button = 0; #10; // Ensure button is released
        button = 1; #8; // Press the button

        $finish;
    end

    // Monitor outputs
    initial begin
        $monitor("Time=%0t | reset=%b | clk=%b | led=%b", $time, reset, clk, led);
    end

endmodule

16-fsm_button/dump.vcd
$date
	Tue Jun 03 14:56:23 2025
$end
$version
	Icarus Verilog
$end
$timescale
	1ps
$end
$scope module button_tb $end
$var wire 1 ! led $end
$var reg 1 " button $end
$var reg 1 # clk $end
$var reg 1 $ reset $end
$scope module uut $end
$var wire 1 " button $end
$var wire 1 # clk $end
$var wire 1 $ reset $end
$var reg 1 ! led $end
$var reg 1 % status $end
$upscope $end
$upscope $end
$enddefinitions $end
#0
$dumpvars
x%
0$
0#
0"
x!
$end
#5000
1#
#10000
0#
#12000
1"
#15000
1#
#20000
0#
#22000
0"
#25000
1#
#30000
0#
#32000
1"
#35000
1#
#40000
0#
#42000
0!
1$
#45000
1#
#50000
0#
#52000
0$
#55000
1#
#60000
0#
#62000
0"
#65000
1#
#70000
0#
#72000
1"
